subtitle_utils-1.0.0.dist-info/METADATA
subtitle_utils-1.0.0.dist-info/WHEEL
subtitle_utils-1.0.0.dist-info/licenses/LICENSE
subtitle_utils/NOTICE.MD
subtitle_utils/__init__.py
subtitle_utils/convert/LICENSE
subtitle_utils/convert/ass.py
subtitle_utils/convert/bcc.py
subtitle_utils/parse.py
subtitle_utils/schema.py
subtitle_utils-1.0.0.dist-info/RECORD
