Metadata-Version: 2.1
Name: subtitle-utils
Version: 1.0.0
Summary: Subtilte Conversion utils - ass2srt vtt2bcc srt2bcc ass2bcc and more
Author-Email: sudoskys <coldlando@hotmail.com>, KimmyXYC <kimmyxyc@gmail.com>
License: MIT
Project-URL: Repository, https://github.com/sudoskys/subtitle_utils
Requires-Python: <3.12,>=3.8
Requires-Dist: pysrt<2.0.0,>=1.1.2
Requires-Dist: pyvtt<1.0.0,>=0.0.4
Requires-Dist: chardet<6.0.0,>=5.1.0
Requires-Dist: pyasstosrt<2.0.0,>=1.3.1
